microsoft/teams/api/__init__.py
microsoft/teams/api/activities/__init__.py
microsoft/teams/api/activities/activity_params.py
microsoft/teams/api/activities/handoff.py
microsoft/teams/api/activities/invoke_activity.py
microsoft/teams/api/activities/protocols.py
microsoft/teams/api/activities/sent_activity.py
microsoft/teams/api/activities/trace.py
microsoft/teams/api/activities/typing.py
microsoft/teams/api/activities/command/__init__.py
microsoft/teams/api/activities/command/command_result.py
microsoft/teams/api/activities/command/command_send.py
microsoft/teams/api/activities/conversation/__init__.py
microsoft/teams/api/activities/conversation/conversation_update.py
microsoft/teams/api/activities/conversation/end_of_conversation.py
microsoft/teams/api/activities/event/__init__.py
microsoft/teams/api/activities/event/meeting_end.py
microsoft/teams/api/activities/event/meeting_participant.py
microsoft/teams/api/activities/event/meeting_participant_join.py
microsoft/teams/api/activities/event/meeting_participant_leave.py
microsoft/teams/api/activities/event/meeting_start.py
microsoft/teams/api/activities/event/read_reciept.py
microsoft/teams/api/activities/install_update/__init__.py
microsoft/teams/api/activities/install_update/add.py
microsoft/teams/api/activities/install_update/remove.py
microsoft/teams/api/activities/invoke/__init__.py
microsoft/teams/api/activities/invoke/execute_action.py
microsoft/teams/api/activities/invoke/file_consent.py
microsoft/teams/api/activities/invoke/handoff_action.py
microsoft/teams/api/activities/invoke/adaptive_card/__init__.py
microsoft/teams/api/activities/invoke/adaptive_card/action.py
microsoft/teams/api/activities/invoke/config/__init__.py
microsoft/teams/api/activities/invoke/config/config_fetch.py
microsoft/teams/api/activities/invoke/config/config_submit.py
microsoft/teams/api/activities/invoke/message/__init__.py
microsoft/teams/api/activities/invoke/message/submit_action.py
microsoft_teams_api-2.0.0a5.dist-info/METADATA
microsoft_teams_api-2.0.0a5.dist-info/WHEEL
microsoft_teams_api-2.0.0a5.dist-info/RECORD
