Metadata-Version: 2.4
Name: microsoft-teams-api
Version: 2.0.0a5
Summary: API package for Microsoft Teams
Project-URL: Homepage, https://github.com/microsoft/teams.py/tree/main/packages/api/src/microsoft/teams/api
Author-email: Microsoft <TeamsAISDKFeedback@microsoft.com>
License-Expression: MIT
Keywords: agents,ai,bot,microsoft,teams
Requires-Python: <3.14,>=3.12
Requires-Dist: microsoft-teams-cards
Requires-Dist: microsoft-teams-common
Requires-Dist: pydantic>=2.0.0
Requires-Dist: pyjwt[crypto]>=2.10.0
